{
  "TRAVEL": {
    "day4": 8000,
    "day5": 10000,
    "number3": 3,
    "day2": 4000,
    "number4": 4,
    "day3": 6000,
    "number1": 1,
    "number2": 2,
    "day1": 2000,
    "number5": 5
  },
  "TRANSPORTATION": {
    "number1": 1600
  },
  "PROFESSIONALTRANSLATION": {
    "day4": 4,
    "day5": 5,
    "day2": 2,
    "day3": 3,
    "day1": 1,
    "type1": 1600
  },
  "HOTELACCOMMODATION": {
    "type5": 6000,
    "type4": 3000,
    "type3": 1400,
    "number3": 3,
    "number4": 4,
    "number1": 1,
    "number2": 2,
    "number5": 5,
    "day4": 4,
    "day5": 5,
    "day2": 2,
    "day3": 3,
    "day1": 1
  },
  "MEALS": {
    "people3": 3,
    "people4": 4,
    "people5": 5,
    "people1": 1,
    "people2": 2,
    "number3": 4200,
    "number4": 5600,
    "number1": 1400,
    "number2": 2800,
    "number5": 7000
  }
}