[{"flag":"1","stop_time":{"date":15,"day":4,"hours":6,"minutes":28,"month":6,"nanos":0,"seconds":0,"time":1626301680000,"timezoneOffset":-480,"year":121},"productId":"1408328209417768960","num":"24","isPersonalized":"0","nameEn":"Mini Ozone Generator Fridge Purifier Odor Cleaner Vegetable Meat Purify Sterilization Disinfection Air Ozonizer USB Charge","saleStatus":"3","sort":1,"isHaveVideo":"HAVE_VIDEO","type":"loc","SELLPRICE":"19.48","PRODUCTTYPE":"0","bigImg":"https://cc-west-usa.oss-accelerate.aliyuncs.com/4280864e-e1ea-4c3c-9699-b738318d8ccd.jpg","start_time":{"date":13,"day":2,"hours":6,"minutes":27,"month":6,"nanos":0,"seconds":0,"time":1626128820000,"timezoneOffset":-480,"year":121},"authorityStatus":"1","PROPERTYKEY":"BATTERY","yiXiaJia":"0","id":"1408328209417768960","timeFlag":"video","salesCount":"0","isCollect":"0","nameVal":"Mini Ozone Generator Fridge Purifier Odor Cleaner Vegetable Meat Purify Sterilization Disinfection Air Ozonizer USB Charge","islist":false,"addMarkStatus":0,"isAut":"0"},{"flag":"1","stop_time":{"date":15,"day":4,"hours":6,"minutes":28,"month":6,"nanos":0,"seconds":0,"time":1626301680000,"timezoneOffset":-480,"year":121},"productId":"1408364511869669376","num":"19","isPersonalized":"0","nameEn":"Bluetooth Fill Light Selfie Stick Outdoor Live Broadcast Integrated Tripod Phone Holder","saleStatus":"3","sort":2,"isHaveVideo":"HAVE_VIDEO","type":"loc","SELLPRICE":"2.48 -- 3.16","PRODUCTTYPE":"0","bigImg":"https://cc-west-usa.oss-accelerate.aliyuncs.com/5d3fac22-a8a2-4e65-bb60-4b789a963936.jpg","start_time":{"date":13,"day":2,"hours":6,"minutes":28,"month":6,"nanos":0,"seconds":0,"time":1626128880000,"timezoneOffset":-480,"year":121},"authorityStatus":"1","PROPERTYKEY":"BATTERY","yiXiaJia":"0","id":"1408364511869669376","timeFlag":"video","salesCount":"0","isCollect":"0","nameVal":"Bluetooth Fill Light Selfie Stick Outdoor Live Broadcast Integrated Tripod Phone Holder","islist":false,"addMarkStatus":0,"isAut":"0"},{"flag":"1","stop_time":{"date":15,"day":4,"hours":6,"minutes":29,"month":6,"nanos":0,"seconds":0,"time":1626301740000,"timezoneOffset":-480,"year":121},"productId":"1407593066453405696","num":"29","isPersonalized":"0","nameEn":"3 Modes Oral Irrigator USB Rechargeable Water Floss Portable Dental Water Flosser Jet 240ml Irrigator Dental Teeth Cleaner","saleStatus":"3","sort":3,"isHaveVideo":"HAVE_VIDEO","type":"loc","SELLPRICE":"6.10","PRODUCTTYPE":"0","bigImg":"https://cc-west-usa.oss-accelerate.aliyuncs.com/2fee7985-6b8b-493b-b2b5-a4ae0da3f3e2.jpg","start_time":{"date":13,"day":2,"hours":6,"minutes":29,"month":6,"nanos":0,"seconds":0,"time":1626128940000,"timezoneOffset":-480,"year":121},"authorityStatus":"1","PROPERTYKEY":"BATTERY","yiXiaJia":"0","id":"1407593066453405696","timeFlag":"video","salesCount":"0","isCollect":"0","nameVal":"3 Modes Oral Irrigator USB Rechargeable Water Floss Portable Dental Water Flosser Jet 240ml Irrigator Dental Teeth Cleaner","islist":false,"addMarkStatus":0,"isAut":"0"},{"flag":"1","stop_time":{"date":15,"day":4,"hours":6,"minutes":29,"month":6,"nanos":0,"seconds":0,"time":1626301740000,"timezoneOffset":-480,"year":121},"productId":"1397784480206426112","num":"29","isPersonalized":"0","nameEn":"Wall-Mounted Silicone Toilet Brush Tool","saleStatus":"3","sort":4,"isHaveVideo":"HAVE_VIDEO","type":"loc","SELLPRICE":"1.05","PRODUCTTYPE":"0","bigImg":"https://cc-west-usa.oss-accelerate.aliyuncs.com/1622092633907.jpg","start_time":{"date":13,"day":2,"hours":6,"minutes":29,"month":6,"nanos":0,"seconds":0,"time":1626128940000,"timezoneOffset":-480,"year":121},"authorityStatus":"1","PROPERTYKEY":"COMMON,OVERSIZE","yiXiaJia":"0","id":"1397784480206426112","timeFlag":"video","salesCount":"0","isCollect":"0","nameVal":"Wall-Mounted Silicone Toilet Brush Tool","islist":false,"addMarkStatus":0,"isAut":"0"},{"flag":"1","stop_time":{"date":15,"day":4,"hours":6,"minutes":29,"month":6,"nanos":0,"seconds":0,"time":1626301740000,"timezoneOffset":-480,"year":121},"productId":"1407984397109563392","num":"13","isPersonalized":"0","nameEn":"Newly Fruit Picker Head Basket Garden Fruit Picking Tools Fruits Catcher For Harvest Picking Citrus Pear Peach Gardening Tool","saleStatus":"3","sort":5,"isHaveVideo":"HAVE_VIDEO","type":"loc","SELLPRICE":"1.05","PRODUCTTYPE":"0","bigImg":"https://cc-west-usa.oss-accelerate.aliyuncs.com/9034489b-5caf-4549-871c-86a138f07167.jpg","start_time":{"date":13,"day":2,"hours":6,"minutes":29,"month":6,"nanos":0,"seconds":0,"time":1626128940000,"timezoneOffset":-480,"year":121},"authorityStatus":"1","PROPERTYKEY":"COMMON","yiXiaJia":"0","id":"1407984397109563392","timeFlag":"video","salesCount":"0","isCollect":"0","nameVal":"Newly Fruit Picker Head Basket Garden Fruit Picking Tools Fruits Catcher For Harvest Picking Citrus Pear Peach Gardening Tool","islist":false,"addMarkStatus":0,"isAut":"0"},{"flag":"1","stop_time":{"date":15,"day":4,"hours":6,"minutes":30,"month":6,"nanos":0,"seconds":0,"time":1626301800000,"timezoneOffset":-480,"year":121},"productId":"1408293364826247168","num":"14","isPersonalized":"0","nameEn":"Desktop Air Cooler Fan Mute USB Mini Conditioner New Style Spray Gift Decorations And Ornaments","saleStatus":"3","sort":6,"isHaveVideo":"HAVE_VIDEO","type":"loc","SELLPRICE":"19.98","PRODUCTTYPE":"0","bigImg":"https://cc-west-usa.oss-accelerate.aliyuncs.com/14e215d2-65b1-439e-8aec-c03c168ba2e5.jpg","start_time":{"date":13,"day":2,"hours":6,"minutes":30,"month":6,"nanos":0,"seconds":0,"time":1626129000000,"timezoneOffset":-480,"year":121},"authorityStatus":"1","PROPERTYKEY":"ELECTRONIC","yiXiaJia":"0","id":"1408293364826247168","timeFlag":"video","salesCount":"0","isCollect":"0","nameVal":"Desktop Air Cooler Fan Mute USB Mini Conditioner New Style Spray Gift Decorations And Ornaments","islist":false,"addMarkStatus":0,"isAut":"0"}]